undetected_geckodriver/__init__.py
undetected_geckodriver/constants.py
undetected_geckodriver/driver.py
undetected_geckodriver/mixins.py
undetected_geckodriver/utils.py
undetected_geckodriver_lw-2.1.0.dist-info/licenses/LICENSE
undetected_geckodriver_lw-2.1.0.dist-info/METADATA
undetected_geckodriver_lw-2.1.0.dist-info/WHEEL
undetected_geckodriver_lw-2.1.0.dist-info/top_level.txt
undetected_geckodriver_lw-2.1.0.dist-info/RECORD
