Metadata-Version: 2.4
Name: undetected-geckodriver-lw
Version: 2.1.0
Summary: A Firefox Selenium WebDriver that patches the browser to avoid detection. Bypasses services such as Cloudflare, Distil Networks, and more. Ideal for web scraping, automated testing, and bot development without getting detected.
Home-page: https://github.com/LunarWatcher/undetected_geckodriver
Author: LunarWatcher
Author-email: oliviawolfie@pm.me
License: MIT
Project-URL: Documentation, https://github.com/LunarWatcher/undetected_geckodriver#readme
Project-URL: Source, https://github.com/LunarWatcher/undetected_geckodriver
Project-URL: Tracker, https://github.com/LunarWatcher/undetected_geckodriver/issues
Project-URL: Changelog, https://github.com/LunarWatcher/undetected_geckodriver/releases
Keywords: selenium firefox webdriver undetected bypass cloudflare distil web scraping automated testing bot development anti-detection automation browser automation
Classifier: Development Status :: 4 - Beta
Classifier: Intended Audience :: Developers
Classifier: Topic :: Software Development :: Testing
Classifier: Topic :: Software Development :: Libraries :: Python Modules
Classifier: Programming Language :: Python :: 3
Classifier: Programming Language :: Python :: 3.6
Classifier: Programming Language :: Python :: 3.7
Classifier: Programming Language :: Python :: 3.8
Classifier: Programming Language :: Python :: 3.9
Classifier: Programming Language :: Python :: 3.10
Classifier: Programming Language :: Python :: 3.11
Classifier: Programming Language :: Python :: 3.12
Classifier: License :: OSI Approved :: MIT License
Classifier: Operating System :: POSIX :: Linux
Classifier: Operating System :: Microsoft :: Windows
Requires-Python: >=3.6
License-File: LICENSE
Requires-Dist: selenium>=4.10.0
Requires-Dist: psutil>=5.8.0
Dynamic: author
Dynamic: author-email
Dynamic: classifier
Dynamic: description
Dynamic: description-content-type
Dynamic: home-page
Dynamic: keywords
Dynamic: license
Dynamic: license-file
Dynamic: project-url
Dynamic: requires-dist
Dynamic: requires-python
Dynamic: summary
